src/__init__.py
src/version_string/__init__.py
src/version_string/main.py
src/version_string/test_main.py
version_string-0.1.dist-info/DESCRIPTION.rst
version_string-0.1.dist-info/METADATA
version_string-0.1.dist-info/RECORD
version_string-0.1.dist-info/WHEEL
version_string-0.1.dist-info/metadata.json
version_string-0.1.dist-info/top_level.txt
