Metadata-Version: 2.0
Name: version-string
Version: 0.1
Summary: compare two string
Home-page: https://github.com/Patibandha/version_string
Author: Meet Patibandha
Author-email: UNKNOWN
License: MIT
Platform: UNKNOWN
